esgp/__init__.py
esgp/esgp_cell.py
esgp/esgp_layer.py
esgp-0.1.0.dist-info/licenses/LICENSE
esgp-0.1.0.dist-info/METADATA
esgp-0.1.0.dist-info/WHEEL
esgp-0.1.0.dist-info/top_level.txt
esgp-0.1.0.dist-info/RECORD
