Metadata-Version: 2.4
Name: esgp
Version: 0.1.0
Summary: Echo State Gradient Propogation implementation for PyTorch
Home-page: https://github.com/RoninAkagami/esgp-net
Author: Ronin Akagami
Author-email: roninakagami@proton.me
Project-URL: Bug Reports, https://github.com/RoninAkagami/esgp-net/issues
Project-URL: Source, https://github.com/RoninAkagami/esgp-net
Keywords: pytorch,reservoir computing,echo state network,esn,esgp
Classifier: Development Status :: 3 - Alpha
Classifier: Intended Audience :: Science/Research
Classifier: License :: OSI Approved :: Apache Software License
Classifier: Programming Language :: Python :: 3
Classifier: Programming Language :: Python :: 3.7
Classifier: Programming Language :: Python :: 3.8
Classifier: Programming Language :: Python :: 3.9
Classifier: Programming Language :: Python :: 3.10
Classifier: Operating System :: OS Independent
Classifier: Topic :: Scientific/Engineering :: Artificial Intelligence
Requires-Python: >=3.7
License-File: LICENSE
Requires-Dist: torch>=1.9.0
Dynamic: author
Dynamic: author-email
Dynamic: classifier
Dynamic: description
Dynamic: description-content-type
Dynamic: home-page
Dynamic: keywords
Dynamic: license-file
Dynamic: project-url
Dynamic: requires-dist
Dynamic: requires-python
Dynamic: summary
